pyde_fem/__init__.py
pyde_fem/assembly.py
pyde_fem/mesh/__init__.py
pyde_fem/mesh/geometry.py
pyde_fem/mesh/io.py
pyde_fem/mesh/plotting.py
pyde_fem-1.0.0.dist-info/LICENSE
pyde_fem-1.0.0.dist-info/METADATA
pyde_fem-1.0.0.dist-info/WHEEL
pyde_fem-1.0.0.dist-info/top_level.txt
pyde_fem-1.0.0.dist-info/RECORD
