Metadata-Version: 2.1
Name: pyde-fem
Version: 1.0.0
Summary: Python package for Finite Element Method (FEM) for solving Partial Differential Equations (PDEs)
Home-page: https://github.com/RyanTmi/pyde-fem
Author: Ryan Timeus
Author-email: timeusryan@gmail.com
License: Apache License 2.0
Keywords: finite element method,partial differential equations,mesh,numerical analysis
Classifier: Intended Audience :: Science/Research
Classifier: Topic :: Scientific/Engineering :: Mathematics
Classifier: Operating System :: OS Independent
Classifier: Programming Language :: Python :: 3.8
Classifier: Programming Language :: Python :: 3.9
Classifier: Programming Language :: Python :: 3.10
Classifier: Programming Language :: Python :: 3.11
Classifier: Programming Language :: Python :: 3.12
Classifier: License :: OSI Approved :: Apache Software License
Requires-Python: >=3.8
License-File: LICENSE
Requires-Dist: matplotlib
Requires-Dist: numpy>=1.26
Requires-Dist: scipy
